[
			{
				"id" : "shop01",
				"name" : "DR.SOS微雕焕肤无痕肌底精华",
				"src" : "5b51402a477be.jpg",
				"price" : "899.99",
				"sell":"1011"
			},
			{
				"id" : "shop02",
				"name" : "韩国进口秘贴焕然修护精华液礼盒",
				"src" : "5af5956dc4dcd.jpg",
				"price" : "299.00",
				"sell":"504"
			},
			{
				"id" : "shop03",
				"name" : "DR.MAXSKIN黄金白藜芦醇尊享组",
				"src" : "5b85145421820.jpg",
				"price" : "299.00",
				"sell":"303"
			},
			{
				"id" : "shop04",
				"name" : "韩国进口DPC肌肤熨斗美容仪",
				"src" : "5b0673dd7c272.jpg",
				"price" : "299.00",
				"sell":"221"
			},
			{
				"id" : "shop05",
				"name" : "京城之霜蜂皇抗皱精华庆生组",
				"src" : "5b9bd3787ad2a.jpg",
				"price" : "263.00",
				"sell":"121"
			}
		]